pyDEMATELSolver/DEMATELSolver.py
pyDEMATELSolver/DEMATELWindow.py
pyDEMATELSolver/FuzzyDEMATELSolver.py
pyDEMATELSolver/__init__.py
pyDEMATEL_Package-0.1.1.dist-info/LICENSE.md
pyDEMATEL_Package-0.1.1.dist-info/METADATA
pyDEMATEL_Package-0.1.1.dist-info/WHEEL
pyDEMATEL_Package-0.1.1.dist-info/top_level.txt
pyDEMATEL_Package-0.1.1.dist-info/RECORD
