Metadata-Version: 2.1
Name: pyDEMATEL_Package
Version: 0.1.1
Summary: pyDematel a python-based tool implementing the Dematel and fuzzy Dematel methods for improved decision making
Home-page: https://github.com/achekry/-Elsevier-SoftwareX-pyDEMATEL
Author: Abderrahman CHEKRY, Jamal Bakkas, Mohamed Hanine
Author-email: a.chekry@uca.ac.ma
Classifier: Programming Language :: Python :: 3
Classifier: License :: OSI Approved :: BSD License
Classifier: Operating System :: OS Independent
Requires-Python: >=3.6
License-File: LICENSE.md
